SEC-DED/sec_ded_vivado/sec_ded_vivado.srcs/sources_1/new/ser_parral_trans.v
`timescale 1ns / 1ps
//////////////////////////////////////////////////////////////////////////////////
// Company: 
// Engineer: 
// 
// Create Date: 2025/11/06 11:13:51
// Design Name: 
// Module Name: ser_parral_trans
// Project Name: 
// Target Devices: 
// Tool Versions: 
// Description: 
// 
// Dependencies: 
// 
// Revision:
// Revision 0.01 - File Created
// Additional Comments:
// 
//////////////////////////////////////////////////////////////////////////////////

module ser_parral_trans #(
    parameter SERIAL_WIDTH = 8,
    parameter PARRAL_WIDTH = 72
) (
    input                         clk,
    input                         rst_n,

    output reg [PARRAL_WIDTH-1:0] o_data_parral,
    output                        o_valid_parral_data,

    input                         i_valid_serial_data,
    input  [SERIAL_WIDTH-1:0]     i_data_serial
);

// 参数检查
initial begin
    if (PARRAL_WIDTH % SERIAL_WIDTH != 0) begin
        $error("PARRAL_WIDTH must be divisible by SERIAL_WIDTH!");
    end
end

localparam NUM_CHUNKS = PARRAL_WIDTH / SERIAL_WIDTH;
localparam CNT_WIDTH  = $clog2(NUM_CHUNKS);

reg [PARRAL_WIDTH-1:0] shift_reg;
reg [CNT_WIDTH-1:0]    cnt;
reg valid_sr;

// 输出 valid
assign o_valid_parral_data = valid_sr;

always @(posedge clk or negedge rst_n) begin
    if (!rst_n) begin
        shift_reg <= {PARRAL_WIDTH{1'b0}};
        cnt       <= {CNT_WIDTH{1'b0}};
        o_data_parral <= {PARRAL_WIDTH{1'b0}};
        valid_sr  <= 1'b0;
    end else begin
        // Default: valid拉低
        valid_sr <= 1'b0;

        if (i_valid_serial_data) begin
            // 将新串行数据放入高位，其他数据右移
            shift_reg <= {i_data_serial, shift_reg[PARRAL_WIDTH - 1 : SERIAL_WIDTH]};

            if (cnt == NUM_CHUNKS - 1) begin
                // 这是最后一个数据块
                o_data_parral <= {i_data_serial, shift_reg[PARRAL_WIDTH - 1 : SERIAL_WIDTH]};
                valid_sr <= 1'b1;
                cnt <= {CNT_WIDTH{1'b0}}; // 回绕到0，准备下一组
                $display("[S2P] Output complete at %0t: 0x%0h", $time, {i_data_serial, shift_reg[PARRAL_WIDTH - 1 : SERIAL_WIDTH]});
            end else begin
                // 继续积累
                cnt <= cnt + 1;
                $display("[S2P] Accumulating byte %0d/8 at %0t: data=0x%03h", cnt, $time, i_data_serial);
            end
        end else begin
            // 无有效输入时，计数器不变
            if (cnt > 0) begin
                $display("[S2P] No input but cnt=%0d (waiting for more data)", cnt);
            end
        end
    end
end

endmodule

SEC-DED/sec_ded_vivado/sec_ded_vivado.srcs/sources_1/new/parral_ser_trans.v
`timescale 1ns / 1ps
//////////////////////////////////////////////////////////////////////////////////
// Module: parral_ser_trans
// Simple parallel-to-serial without FIFO
// Input: 72-bit parallel, Output: 8-bit serial (one byte per cycle)
//////////////////////////////////////////////////////////////////////////////////

module parral_ser_trans #(
    parameter PARRAL_WIDTH = 72,
    parameter SERIAL_WIDTH = 8
) (
    input                   clk,
    input                   rst_n,
    input                   i_valid_parral,
    input [PARRAL_WIDTH-1:0] i_data_parral,
    output                  o_valid_serial,
    output [SERIAL_WIDTH-1:0] o_data_serial,
    output reg              error
);

localparam NUM_CHUNKS = PARRAL_WIDTH / SERIAL_WIDTH;
localparam CNT_WIDTH = $clog2(NUM_CHUNKS);

reg [PARRAL_WIDTH-1:0] shift_reg;
reg [CNT_WIDTH-1:0]    cnt;
reg                    busy;

// Output assignment
assign o_valid_serial = busy;
assign o_data_serial = shift_reg[SERIAL_WIDTH-1:0];

always @(posedge clk or negedge rst_n) begin
    if (!rst_n) begin
        shift_reg <= {PARRAL_WIDTH{1'b0}};
        cnt       <= {CNT_WIDTH{1'b0}};
        busy      <= 1'b0;
        error     <= 1'b0;
    end 
    else begin
        error <= 1'b0;

        // Check if we've finished sending all 9 bytes
        if (cnt == NUM_CHUNKS - 1) begin
            // Last byte is being sent this cycle
            if (i_valid_parral) begin
                // New input arrives at the same time! Switch immediately
                shift_reg <= i_data_parral;
                cnt <= 0;
                busy <= 1'b1;
                $display("[P2S] SWITCH: new input=0x%h", i_data_parral);
            end else begin
                // No new input, go idle
                busy <= 1'b0;
                $display("[P2S] DONE at cnt=%0d\n", cnt);
            end
        end else if (busy) begin
            // Continue sending
            cnt <= cnt + 1;
            shift_reg <= shift_reg >> SERIAL_WIDTH;
        end else if (i_valid_parral) begin
            // Start new transmission (not busy)
            shift_reg <= i_data_parral;
            busy <= 1'b1;
            cnt <= 0;
            $display("[P2S] START: input=0x%h", i_data_parral);
        end
    end
end

endmodule

SEC-DED/sec_ded_vivado/sec_ded_vivado.srcs/sim_1/new/tb_serpara_trans.v


`timescale 1ns / 1ps

module tb_serpara_trans;
    // Parameters to match modules
    localparam PARRAL_WIDTH = 72;
    localparam SERIAL_WIDTH = 8;
    localparam WORDS = PARRAL_WIDTH / SERIAL_WIDTH;

    reg clk;
    reg rst_n;
    reg i_valid_parral;
    reg [PARRAL_WIDTH-1:0] i_data_parral;

    wire o_valid_serial;
    wire [SERIAL_WIDTH-1:0] o_data_serial;

    wire [PARRAL_WIDTH-1:0] o_data_parral;
    wire o_valid_parral_data;

    // instantiate modules with matching parameters
    parral_ser_trans #(.PARRAL_WIDTH(PARRAL_WIDTH), .SERIAL_WIDTH(SERIAL_WIDTH)) p2s (
        .clk(clk),
        .rst_n(rst_n),
        .i_valid_parral(i_valid_parral),
        .i_data_parral(i_data_parral),
        .o_valid_serial(o_valid_serial),
        .o_data_serial(o_data_serial)
    );

    ser_parral_trans #(.SERIAL_WIDTH(SERIAL_WIDTH), .PARRAL_WIDTH(PARRAL_WIDTH)) s2p (
        .clk(clk),
        .rst_n(rst_n),
        .o_data_parral(o_data_parral),
        .o_valid_parral_data(o_valid_parral_data),
        .i_valid_serial_data(o_valid_serial),
        .i_data_serial(o_data_serial)
    );

    // clock
    initial begin
        clk = 1; forever #5 clk = ~clk; // 100MHz
    end

    initial begin
        $dumpfile("tb_serpara_trans.vcd");
        $dumpvars(0, tb_serpara_trans);

        // Initialize
        rst_n = 1'b0;
        i_valid_parral = 1'b0;
        i_data_parral = {PARRAL_WIDTH{1'b0}};
        repeat(5) @(posedge clk);
        rst_n = 1'b1;
        repeat(2) @(posedge clk);

        $display("\n\n");
        $display("================================================================================");
        $display("TEST 1: Single vector roundtrip tests (P2S -> S2P loopback)");
        $display("================================================================================");
        // test vectors
        test_one(72'h0123_4567_89AB_CDEF_012);
        test_one({8'hAA,8'h55,8'hFF,8'h00,8'h11,8'h22,8'h33,8'h44,8'h66});
        test_one({72{1'b1}});
        test_one(72'h0);

        // Wait between test groups
        repeat(5) @(posedge clk);

        $display("\n\n================================================================================");
        $display("tb_serpara_trans finished");
        $display("================================================================================\n");
        $finish;
    end

    task test_one(input [PARRAL_WIDTH-1:0] vec);
        integer i, j;
        reg [PARRAL_WIDTH-1:0] collected;
        integer widx;
        reg [PARRAL_WIDTH-1:0] recovered;
        reg recovered_valid;
        begin
            $display("\n[TEST] Input vector: 0x%018h (repeating every %0d cycles)", vec, WORDS);
            
            // Collect serial outputs for multiple cycles
            // Repeat input every WORDS cycles to test continuous stream
            collected = {PARRAL_WIDTH{1'b0}};
            widx = 0;
            recovered = {PARRAL_WIDTH{1'b0}};
            recovered_valid = 1'b0;
            
            $display("  Cycle | P2S Valid | P2S Data | S2P Valid | S2P Data");
            $display("  ------|-----------|----------|-----------|----------");
            
            for (j = 0; j < 3; j = j + 1) begin
                // Drive input valid pulse (single cycle pulse)
                @(posedge clk);
                i_data_parral = vec;
                i_valid_parral = 1'b1;
                @(posedge clk);
                i_valid_parral = 1'b0;
                
                // Now we've consumed 2 cycles from the 9-cycle window
                // Wait for remaining 7 cycles (total 9 cycles including the 2 drive cycles)
                for (i = 0; i < WORDS - 2; i = i + 1) begin
                    @(posedge clk);
                    
                    // Log this cycle
                    if (o_valid_serial && o_valid_parral_data) begin
                        $display("  %5d |    1      | 0x%02h    |    1      | 0x%018h", 
                                 j*WORDS+i, o_data_serial, o_data_parral);
                    end
                    else if (o_valid_serial) begin
                        $display("  %5d |    1      | 0x%02h    |    0      | -", 
                                 j*WORDS+i, o_data_serial);
                    end
                    else if (o_valid_parral_data) begin
                        $display("  %5d |    0      | -        |    1      | 0x%018h", 
                                 j*WORDS+i, o_data_parral);
                    end
                    else begin
                        $display("  %5d |    0      | -        |    0      | -", j*WORDS+i);
                    end
                    
                    // Collect serial data
                    if (o_valid_serial) begin
                        collected[widx*SERIAL_WIDTH +: SERIAL_WIDTH] = o_data_serial;
                        widx = widx + 1;
                    end
                    
                    // Capture parallel data when valid
                    if (o_valid_parral_data) begin
                        recovered = o_data_parral;
                        recovered_valid = 1'b1;
                    end
                end
            end

            // Verify results
            $display("\n  Results:");
            $display("    Input vector:    0x%018h", vec);
            $display("    Collected serial: 0x%018h (from %0d bytes)", collected, widx);
            $display("    S2P output:       0x%018h (valid=%b)", recovered, recovered_valid);
            
            if (recovered_valid && recovered == vec) begin
                $display("     PASS: At least one cycle completed successfully!\n");
            end
            else begin
                $display("     FAIL: Issues detected!\n");
                if (!recovered_valid)
                    $display("      - S2P never produced valid output");
                if (recovered != vec && recovered_valid)
                    $display("      - S2P output mismatch");
            end

            // Wait before next test
            //repeat(1) @(posedge clk);
        end
    endtask

endmodule

SEC-DED/sec_ded_vivado/sec_ded_vivado.sim/sim_1/behav/xsim/tb_serpara_trans.vcd
$date
   Thu Nov  6 18:49:14 2025
$end

$version
  2024.2.0
  $dumpfile ("tb_serpara_trans.vcd") 
$end

$timescale
  1ps
$end

$scope module tb_serpara_trans $end
$var reg 1 ! clk $end
$var reg 1 " rst_n $end
$var reg 1 # i_valid_parral $end
$var reg 72 $ i_data_parral [71:0] $end
$var wire 1 % o_valid_serial $end
$var wire 8 & o_data_serial [7:0] $end
$var wire 72 ' o_data_parral [71:0] $end
$var wire 1 ( o_valid_parral_data $end
$scope module p2s $end
$var wire 1 ) clk $end
$var wire 1 * rst_n $end
$var wire 1 + i_valid_parral $end
$var wire 72 , i_data_parral [71:0] $end
$var wire 1 % o_valid_serial $end
$var wire 8 & o_data_serial [7:0] $end
$var reg 1 - error $end
$var reg 72 . shift_reg [71:0] $end
$var reg 4 / cnt [3:0] $end
$var reg 1 0 busy $end
$upscope $end
$scope module s2p $end
$var wire 1 1 clk $end
$var wire 1 2 rst_n $end
$var reg 72 3 o_data_parral [71:0] $end
$var wire 1 ( o_valid_parral_data $end
$var wire 1 % i_valid_serial_data $end
$var wire 8 & i_data_serial [7:0] $end
$var reg 72 4 shift_reg [71:0] $end
$var reg 4 5 cnt [3:0] $end
$var reg 1 6 valid_sr $end
$upscope $end
$scope task test_one $end
$var reg 72 7 vec [71:0] $end
$var integer 32 8 i [31:0] $end
$var integer 32 9 j [31:0] $end
$var reg 72 : collected [71:0] $end
$var integer 32 ; widx [31:0] $end
$var reg 72 < recovered [71:0] $end
$var reg 1 = recovered_valid $end
$upscope $end
$upscope $end
$enddefinitions $end

#0
$dumpvars
1!
0"
0#
b0 $
0%
b0 &
b0 '
0(
1)
0*
0+
b0 ,
0-
b0 .
b0 /
00
11
02
b0 3
b0 4
b0 5
06
bx 7
bx 8
bx 9
bx :
bx ;
bx <
x=
$end

#5000
0!
0)
01

#10000
1!
1)
11

#15000
0!
0)
01

#20000
1!
1)
11

#25000
0!
0)
01

#30000
1!
1)
11

#35000
0!
0)
01

#40000
1!
1)
11

#45000
0!
0)
01

#50000
1!
1"
1)
1*
11
12

#55000
0!
0)
01

#60000
1!
1)
11

#65000
0!
0)
01

#70000
1!
1)
11
b100100011010001010110011110001001101010111100110111101111000000010010 7
b0 9
b0 :
b0 ;
b0 <
0=

#75000
0!
0)
01

#80000
1!
1#
b100100011010001010110011110001001101010111100110111101111000000010010 $
1%
b10010 &
1)
1+
b100100011010001010110011110001001101010111100110111101111000000010010 ,
b100100011010001010110011110001001101010111100110111101111000000010010 .
10
11

#85000
0!
0)
01

#90000
1!
0#
b11110000 &
1)
0+
b1001000110100010101100111100010011010101111001101111011110000 .
b1 /
11
b100100000000000000000000000000000000000000000000000000000000000000000 4
b1 5
b0 8

#95000
0!
0)
01

#100000
1!
b11011110 &
1)
b10010001101000101011001111000100110101011110011011110 .
b10 /
11
b111100000001001000000000000000000000000000000000000000000000000000000000 4
b10 5
b1 8
b11110000 :
b1 ;

#105000
0!
0)
01

#110000
1!
b10111100 &
1)
b100100011010001010110011110001001101010111100 .
b11 /
11
b110111101111000000010010000000000000000000000000000000000000000000000000 4
b11 5
b10 8
b1101111011110000 :
b10 ;

#115000
0!
0)
01

#120000
1!
b10011010 &
1)
b1001000110100010101100111100010011010 .
b100 /
11
b101111001101111011110000000100100000000000000000000000000000000000000000 4
b100 5
b11 8
b101111001101111011110000 :
b11 ;

#125000
0!
0)
01

#130000
1!
b1111000 &
1)
b10010001101000101011001111000 .
b101 /
11
b100110101011110011011110111100000001001000000000000000000000000000000000 4
b101 5
b100 8
b10011010101111001101111011110000 :
b100 ;

#135000
0!
0)
01

#140000
1!
b1010110 &
1)
b100100011010001010110 .
b110 /
11
b11110001001101010111100110111101111000000010010000000000000000000000000 4
b110 5
b101 8
b111100010011010101111001101111011110000 :
b101 ;

#145000
0!
0)
01

#150000
1!
b110100 &
1)
b1001000110100 .
b111 /
11
b10101100111100010011010101111001101111011110000000100100000000000000000 4
b111 5
b110 8
b10101100111100010011010101111001101111011110000 :
b110 ;

#155000
0!
0)
01

#160000
1!
b10010 &
1)
b10010 .
b1000 /
11
b1101000101011001111000100110101011110011011110111100000001001000000000 4
b1000 5
b111 8
b1 9
b110100010101100111100010011010101111001101111011110000 :
b111 ;

#165000
0!
0)
01

#170000
1!
1#
b100100011010001010110011110001001101010111100110111101111000000010010 '
1(
1)
1+
b100100011010001010110011110001001101010111100110111101111000000010010 .
b0 /
11
b100100011010001010110011110001001101010111100110111101111000000010010 3
b100100011010001010110011110001001101010111100110111101111000000010010 4
b0 5
16

#175000
0!
0)
01

#180000
1!
0#
b11110000 &
0(
1)
0+
b1001000110100010101100111100010011010101111001101111011110000 .
b1 /
11
b100100001001000110100010101100111100010011010101111001101111011110000 4
b1 5
06
b0 8

#185000
0!
0)
01

#190000
1!
b11011110 &
1)
b10010001101000101011001111000100110101011110011011110 .
b10 /
11
b111100000001001000010010001101000101011001111000100110101011110011011110 4
b10 5
b1 8
b1111000000110100010101100111100010011010101111001101111011110000 :
b1000 ;

#195000
0!
0)
01

#200000
1!
b10111100 &
1)
b100100011010001010110011110001001101010111100 .
b11 /
11
b110111101111000000010010000100100011010001010110011110001001101010111100 4
b11 5
b10 8
b110111101111000000110100010101100111100010011010101111001101111011110000 :
b1001 ;

#205000
0!
0)
01

#210000
1!
b10011010 &
1)
b1001000110100010101100111100010011010 .
b100 /
11
b101111001101111011110000000100100001001000110100010101100111100010011010 4
b100 5
b11 8
b1010 ;

#215000
0!
0)
01

#220000
1!
b1111000 &
1)
b10010001101000101011001111000 .
b101 /
11
b100110101011110011011110111100000001001000010010001101000101011001111000 4
b101 5
b100 8
b1011 ;

#225000
0!
0)
01

#230000
1!
b1010110 &
1)
b100100011010001010110 .
b110 /
11
b11110001001101010111100110111101111000000010010000100100011010001010110 4
b110 5
b101 8
b1100 ;

#235000
0!
0)
01

#240000
1!
b110100 &
1)
b1001000110100 .
b111 /
11
b10101100111100010011010101111001101111011110000000100100001001000110100 4
b111 5
b110 8
b1101 ;

#245000
0!
0)
01

#250000
1!
b10010 &
1)
b10010 .
b1000 /
11
b1101000101011001111000100110101011110011011110111100000001001000010010 4
b1000 5
b111 8
b10 9
b1110 ;

#255000
0!
0)
01

#260000
1!
1#
1(
1)
1+
b100100011010001010110011110001001101010111100110111101111000000010010 .
b0 /
11
b100100011010001010110011110001001101010111100110111101111000000010010 4
b0 5
16

#265000
0!
0)
01

#270000
1!
0#
b11110000 &
0(
1)
0+
b1001000110100010101100111100010011010101111001101111011110000 .
b1 /
11
b100100001001000110100010101100111100010011010101111001101111011110000 4
b1 5
06
b0 8

#275000
0!
0)
01

#280000
1!
b11011110 &
1)
b10010001101000101011001111000100110101011110011011110 .
b10 /
11
b111100000001001000010010001101000101011001111000100110101011110011011110 4
b10 5
b1 8
b1111 ;

#285000
0!
0)
01

#290000
1!
b10111100 &
1)
b100100011010001010110011110001001101010111100 .
b11 /
11
b110111101111000000010010000100100011010001010110011110001001101010111100 4
b11 5
b10 8
b10000 ;

#295000
0!
0)
01

#300000
1!
b10011010 &
1)
b1001000110100010101100111100010011010 .
b100 /
11
b101111001101111011110000000100100001001000110100010101100111100010011010 4
b100 5
b11 8
b10001 ;

#305000
0!
0)
01

#310000
1!
b1111000 &
1)
b10010001101000101011001111000 .
b101 /
11
b100110101011110011011110111100000001001000010010001101000101011001111000 4
b101 5
b100 8
b10010 ;

#315000
0!
0)
01

#320000
1!
b1010110 &
1)
b100100011010001010110 .
b110 /
11
b11110001001101010111100110111101111000000010010000100100011010001010110 4
b110 5
b101 8
b10011 ;

#325000
0!
0)
01

#330000
1!
b110100 &
1)
b1001000110100 .
b111 /
11
b10101100111100010011010101111001101111011110000000100100001001000110100 4
b111 5
b110 8
b10100 ;

#335000
0!
0)
01

#340000
1!
b10010 &
1)
b10010 .
b1000 /
11
b1101000101011001111000100110101011110011011110111100000001001000010010 4
b1000 5
b101010100101010111111111000000000001000100100010001100110100010001100110 7
b111 8
b0 9
b0 :
b0 ;

#345000
0!
0)
01

#350000
1!
1#
b101010100101010111111111000000000001000100100010001100110100010001100110 $
b1100110 &
1(
1)
1+
b101010100101010111111111000000000001000100100010001100110100010001100110 ,
b101010100101010111111111000000000001000100100010001100110100010001100110 .
b0 /
11
b100100011010001010110011110001001101010111100110111101111000000010010 4
b0 5
16

#355000
0!
0)
01

#360000
1!
0#
b1000100 &
0(
1)
0+
b1010101001010101111111110000000000010001001000100011001101000100 .
b1 /
11
b11001100001001000110100010101100111100010011010101111001101111011110000 4
b1 5
06
b0 8

#365000
0!
0)
01

#370000
1!
b110011 &
1)
b10101010010101011111111100000000000100010010001000110011 .
b10 /
11
b10001000110011000010010001101000101011001111000100110101011110011011110 4
b10 5
b1 8
b1000100 :
b1 ;

#375000
0!
0)
01

#380000
1!
b100010 &
1)
b101010100101010111111111000000000001000100100010 .
b11 /
11
b1100110100010001100110000100100011010001010110011110001001101010111100 4
b11 5
b10 8
b11001101000100 :
b10 ;

#385000
0!
0)
01

#390000
1!
b10001 &
1)
b1010101001010101111111110000000000010001 .
b100 /
11
b1000100011001101000100011001100001001000110100010101100111100010011010 4
b100 5
b11 8
b1000100011001101000100 :
b11 ;

#395000
0!
0)
01

#400000
1!
b0 &
1)
b10101010010101011111111100000000 .
b101 /
11
b100010010001000110011010001000110011000010010001101000101011001111000 4
b101 5
b100 8
b10001001000100011001101000100 :
b100 ;

#405000
0!
0)
01

#410000
1!
b11111111 &
1)
b101010100101010111111111 .
b110 /
11
b1000100100010001100110100010001100110000100100011010001010110 4
b110 5
b101 8
b101 ;

#415000
0!
0)
01

#420000
1!
b1010101 &
1)
b1010101001010101 .
b111 /
11
b111111110000000000010001001000100011001101000100011001100001001000110100 4
b111 5
b110 8
b111111110000000000010001001000100011001101000100 :
b110 ;

#425000
0!
0)
01

#430000
1!
b10101010 &
1)
b10101010 .
b1000 /
11
b10101011111111100000000000100010010001000110011010001000110011000010010 4
b1000 5
b111 8
b1 9
b1010101111111110000000000010001001000100011001101000100 :
b111 ;

#435000
0!
0)
01

#440000
1!
1#
b1100110 &
b101010100101010111111111000000000001000100100010001100110100010001100110 '
1(
1)
1+
b101010100101010111111111000000000001000100100010001100110100010001100110 .
b0 /
11
b101010100101010111111111000000000001000100100010001100110100010001100110 3
b101010100101010111111111000000000001000100100010001100110100010001100110 4
b0 5
16

#445000
0!
0)
01

#450000
1!
0#
b1000100 &
0(
1)
0+
b1010101001010101111111110000000000010001001000100011001101000100 .
b1 /
11
b11001101010101001010101111111110000000000010001001000100011001101000100 4
b1 5
06
b0 8

#455000
0!
0)
01

#460000
1!
b110011 &
1)
b10101010010101011111111100000000000100010010001000110011 .
b10 /
11
b10001000110011010101010010101011111111100000000000100010010001000110011 4
b10 5
b1 8
b100010001010101111111110000000000010001001000100011001101000100 :
b1000 ;

#465000
0!
0)
01

#470000
1!
b100010 &
1)
b101010100101010111111111000000000001000100100010 .
b11 /
11
b1100110100010001100110101010100101010111111111000000000001000100100010 4
b11 5
b10 8
b1100110100010001010101111111110000000000010001001000100011001101000100 :
b1001 ;

#475000
0!
0)
01

#480000
1!
b10001 &
1)
b1010101001010101111111110000000000010001 .
b100 /
11
b1000100011001101000100011001101010101001010101111111110000000000010001 4
b100 5
b11 8
b1010 ;

#485000
0!
0)
01

#490000
1!
b0 &
1)
b10101010010101011111111100000000 .
b101 /
11
b100010010001000110011010001000110011010101010010101011111111100000000 4
b101 5
b100 8
b1011 ;

#495000
0!
0)
01

#500000
1!
b11111111 &
1)
b101010100101010111111111 .
b110 /
11
b1000100100010001100110100010001100110101010100101010111111111 4
b110 5
b101 8
b1100 ;

#505000
0!
0)
01

#510000
1!
b1010101 &
1)
b1010101001010101 .
b111 /
11
b111111110000000000010001001000100011001101000100011001101010101001010101 4
b111 5
b110 8
b1101 ;

#515000
0!
0)
01

#520000
1!
b10101010 &
1)
b10101010 .
b1000 /
11
b10101011111111100000000000100010010001000110011010001000110011010101010 4
b1000 5
b111 8
b10 9
b1110 ;

#525000
0!
0)
01

#530000
1!
1#
b1100110 &
1(
1)
1+
b101010100101010111111111000000000001000100100010001100110100010001100110 .
b0 /
11
b101010100101010111111111000000000001000100100010001100110100010001100110 4
b0 5
16

#535000
0!
0)
01

#540000
1!
0#
b1000100 &
0(
1)
0+
b1010101001010101111111110000000000010001001000100011001101000100 .
b1 /
11
b11001101010101001010101111111110000000000010001001000100011001101000100 4
b1 5
06
b0 8

#545000
0!
0)
01

#550000
1!
b110011 &
1)
b10101010010101011111111100000000000100010010001000110011 .
b10 /
11
b10001000110011010101010010101011111111100000000000100010010001000110011 4
b10 5
b1 8
b1111 ;

#555000
0!
0)
01

#560000
1!
b100010 &
1)
b101010100101010111111111000000000001000100100010 .
b11 /
11
b1100110100010001100110101010100101010111111111000000000001000100100010 4
b11 5
b10 8
b10000 ;

#565000
0!
0)
01

#570000
1!
b10001 &
1)
b1010101001010101111111110000000000010001 .
b100 /
11
b1000100011001101000100011001101010101001010101111111110000000000010001 4
b100 5
b11 8
b10001 ;

#575000
0!
0)
01

#580000
1!
b0 &
1)
b10101010010101011111111100000000 .
b101 /
11
b100010010001000110011010001000110011010101010010101011111111100000000 4
b101 5
b100 8
b10010 ;

#585000
0!
0)
01

#590000
1!
b11111111 &
1)
b101010100101010111111111 .
b110 /
11
b1000100100010001100110100010001100110101010100101010111111111 4
b110 5
b101 8
b10011 ;

#595000
0!
0)
01

#600000
1!
b1010101 &
1)
b1010101001010101 .
b111 /
11
b111111110000000000010001001000100011001101000100011001101010101001010101 4
b111 5
b110 8
b10100 ;

#605000
0!
0)
01

#610000
1!
b10101010 &
1)
b10101010 .
b1000 /
11
b10101011111111100000000000100010010001000110011010001000110011010101010 4
b1000 5
b111111111111111111111111111111111111111111111111111111111111111111111111 7
b111 8
b0 9
b0 :
b0 ;

#615000
0!
0)
01

#620000
1!
1#
b111111111111111111111111111111111111111111111111111111111111111111111111 $
b11111111 &
1(
1)
1+
b111111111111111111111111111111111111111111111111111111111111111111111111 ,
b111111111111111111111111111111111111111111111111111111111111111111111111 .
b0 /
11
b101010100101010111111111000000000001000100100010001100110100010001100110 4
b0 5
16

#625000
0!
0)
01

#630000
1!
0#
0(
1)
0+
b1111111111111111111111111111111111111111111111111111111111111111 .
b1 /
11
b111111111010101001010101111111110000000000010001001000100011001101000100 4
b1 5
06
b0 8

#635000
0!
0)
01

#640000
1!
1)
b11111111111111111111111111111111111111111111111111111111 .
b10 /
11
b111111111111111110101010010101011111111100000000000100010010001000110011 4
b10 5
b1 8
b11111111 :
b1 ;

#645000
0!
0)
01

#650000
1!
1)
b111111111111111111111111111111111111111111111111 .
b11 /
11
b111111111111111111111111101010100101010111111111000000000001000100100010 4
b11 5
b10 8
b1111111111111111 :
b10 ;

#655000
0!
0)
01

#660000
1!
1)
b1111111111111111111111111111111111111111 .
b100 /
11
b111111111111111111111111111111111010101001010101111111110000000000010001 4
b100 5
b11 8
b111111111111111111111111 :
b11 ;

#665000
0!
0)
01

#670000
1!
1)
b11111111111111111111111111111111 .
b101 /
11
b111111111111111111111111111111111111111110101010010101011111111100000000 4
b101 5
b100 8
b11111111111111111111111111111111 :
b100 ;

#675000
0!
0)
01

#680000
1!
1)
b111111111111111111111111 .
b110 /
11
b111111111111111111111111111111111111111111111111101010100101010111111111 4
b110 5
b101 8
b1111111111111111111111111111111111111111 :
b101 ;

#685000
0!
0)
01

#690000
1!
1)
b1111111111111111 .
b111 /
11
b111111111111111111111111111111111111111111111111111111111010101001010101 4
b111 5
b110 8
b111111111111111111111111111111111111111111111111 :
b110 ;

#695000
0!
0)
01

#700000
1!
1)
b11111111 .
b1000 /
11
b111111111111111111111111111111111111111111111111111111111111111110101010 4
b1000 5
b111 8
b1 9
b11111111111111111111111111111111111111111111111111111111 :
b111 ;

#705000
0!
0)
01

#710000
1!
1#
b111111111111111111111111111111111111111111111111111111111111111111111111 '
1(
1)
1+
b111111111111111111111111111111111111111111111111111111111111111111111111 .
b0 /
11
b111111111111111111111111111111111111111111111111111111111111111111111111 3
b111111111111111111111111111111111111111111111111111111111111111111111111 4
b0 5
16

#715000
0!
0)
01

#720000
1!
0#
0(
1)
0+
b1111111111111111111111111111111111111111111111111111111111111111 .
b1 /
11
b1 5
06
b0 8

#725000
0!
0)
01

#730000
1!
1)
b11111111111111111111111111111111111111111111111111111111 .
b10 /
11
b10 5
b1 8
b1111111111111111111111111111111111111111111111111111111111111111 :
b1000 ;

#735000
0!
0)
01

#740000
1!
1)
b111111111111111111111111111111111111111111111111 .
b11 /
11
b11 5
b10 8
b111111111111111111111111111111111111111111111111111111111111111111111111 :
b1001 ;

#745000
0!
0)
01

#750000
1!
1)
b1111111111111111111111111111111111111111 .
b100 /
11
b100 5
b11 8
b1010 ;

#755000
0!
0)
01

#760000
1!
1)
b11111111111111111111111111111111 .
b101 /
11
b101 5
b100 8
b1011 ;

#765000
0!
0)
01

#770000
1!
1)
b111111111111111111111111 .
b110 /
11
b110 5
b101 8
b1100 ;

#775000
0!
0)
01

#780000
1!
1)
b1111111111111111 .
b111 /
11
b111 5
b110 8
b1101 ;

#785000
0!
0)
01

#790000
1!
1)
b11111111 .
b1000 /
11
b1000 5
b111 8
b10 9
b1110 ;

#795000
0!
0)
01

#800000
1!
1#
1(
1)
1+
b111111111111111111111111111111111111111111111111111111111111111111111111 .
b0 /
11
b0 5
16

#805000
0!
0)
01

#810000
1!
0#
0(
1)
0+
b1111111111111111111111111111111111111111111111111111111111111111 .
b1 /
11
b1 5
06
b0 8

#815000
0!
0)
01

#820000
1!
1)
b11111111111111111111111111111111111111111111111111111111 .
b10 /
11
b10 5
b1 8
b1111 ;

#825000
0!
0)
01

#830000
1!
1)
b111111111111111111111111111111111111111111111111 .
b11 /
11
b11 5
b10 8
b10000 ;

#835000
0!
0)
01

#840000
1!
1)
b1111111111111111111111111111111111111111 .
b100 /
11
b100 5
b11 8
b10001 ;

#845000
0!
0)
01

#850000
1!
1)
b11111111111111111111111111111111 .
b101 /
11
b101 5
b100 8
b10010 ;

#855000
0!
0)
01

#860000
1!
1)
b111111111111111111111111 .
b110 /
11
b110 5
b101 8
b10011 ;

#865000
0!
0)
01

#870000
1!
1)
b1111111111111111 .
b111 /
11
b111 5
b110 8
b10100 ;

#875000
0!
0)
01

#880000
1!
1)
b11111111 .
b1000 /
11
b1000 5
b0 7
b111 8
b0 9
b0 :
b0 ;

#885000
0!
0)
01

#890000
1!
1#
b0 $
b0 &
1(
1)
1+
b0 ,
b0 .
b0 /
11
b0 5
16

#895000
0!
0)
01

#900000
1!
0#
0(
1)
0+
b1 /
11
b1111111111111111111111111111111111111111111111111111111111111111 4
b1 5
06
b0 8

#905000
0!
0)
01

#910000
1!
1)
b10 /
11
b11111111111111111111111111111111111111111111111111111111 4
b10 5
b1 8
b1 ;

#915000
0!
0)
01

#920000
1!
1)
b11 /
11
b111111111111111111111111111111111111111111111111 4
b11 5
b10 8
b10 ;

#925000
0!
0)
01

#930000
1!
1)
b100 /
11
b1111111111111111111111111111111111111111 4
b100 5
b11 8
b11 ;

#935000
0!
0)
01

#940000
1!
1)
b101 /
11
b11111111111111111111111111111111 4
b101 5
b100 8
b100 ;

#945000
0!
0)
01

#950000
1!
1)
b110 /
11
b111111111111111111111111 4
b110 5
b101 8
b101 ;

#955000
0!
0)
01

#960000
1!
1)
b111 /
11
b1111111111111111 4
b111 5
b110 8
b110 ;

#965000
0!
0)
01

#970000
1!
1)
b1000 /
11
b11111111 4
b1000 5
b111 8
b1 9
b111 ;

#975000
0!
0)
01

#980000
1!
1#
b0 '
1(
1)
1+
b0 /
11
b0 3
b0 4
b0 5
16

#985000
0!
0)
01

#990000
1!
0#
0(
1)
0+
b1 /
11
b1 5
06
b0 8

#995000
0!
0)
01

#1000000
1!
1)
b10 /
11
b10 5
b1 8
b1000 ;
