SEC-DED/sec_ded_vivado/sec_ded_vivado.srcs/sources_1/new/sec_encoder.v
`timescale 1ns / 1ps
//////////////////////////////////////////////////////////////////////////////////
// Company: 
// Engineer: 
// 
// Create Date: 2025/11/06 11:13:51
// Design Name: 
// Module Name: sec_encoder
// Project Name: 
// Target Devices: 
// Tool Versions: 
// Description: 
// 
// Dependencies: 
// 
// Revision:
// Revision 0.01 - File Created
// Additional Comments:
// 
//////////////////////////////////////////////////////////////////////////////////


module sec_encoder
(
    input clk
,   input rst_n

,   input [63:0] i_data
,   input i_valid_datain

,   output reg i_valid_dataout
,   output reg [71:0] o_data_crypt
    );
// Implementation notes:
// - Codeword positions are 1..72 (1-based). We map them into vector indexes [0]=pos1 ... [71]=pos72.
// - Parity bits (Hamming) are placed at positions 1,2,4,8,16,32,64 (powers of two).
// - Overall parity (for DED) is placed at position 72 (the last bit).
// - Data bits (64 bits) are filled into positions that are NOT the parity positions nor position 72,
//   in ascending order: i_data[0] -> lowest data position, etc. The decoder uses the same mapping.

    integer pos, p, d_idx;
    reg [71:0] tmp;
    reg parity_bit;

    always @(*) begin
        // clear
        tmp = 72'b0;
        // place data bits into non-parity positions (positions 1..72, skip powers of two and pos 72)
        d_idx = 0;
        for (pos = 1; pos <= 72; pos = pos + 1) begin
            // skip parity positions 1,2,4,8,16,32,64 and overall parity pos 72
            if (pos == 72 || (pos & (pos - 1)) == 0) begin
                // parity / overall parity: leave for later
            end else begin
                if (d_idx < 64) begin
                    tmp[pos-1] = i_data[d_idx];
                end else begin
                    tmp[pos-1] = 1'b0; // safety
                end
                d_idx = d_idx + 1;
            end
        end

        // compute Hamming parity bits for positions 1,2,4,8,16,32,64
        // Only XOR data bit positions (skip all parity positions and overall parity at pos 72)
        for (p = 0; p < 7; p = p + 1) begin:Hamming_parity_compute
            integer pow2;
            pow2 = 1 << p; // parity position (1-based)
            parity_bit = 1'b0;
            for (pos = 1; pos <= 72; pos = pos + 1) begin
                // skip parity positions and overall parity
                if (pos == pow2 || pos == 72 || (pos & (pos - 1)) == 0) begin
                    // skip parity/overall parity positions
                end else begin
                    if ((pos & pow2) != 0) begin
                        parity_bit = parity_bit ^ tmp[pos-1];
                    end
                end
            end
            tmp[pow2-1] = parity_bit; // write parity
        end

        // compute overall parity (even) placed at position 72
        // overall parity is XOR of bits at positions 1..71 (first 71 bits)
        tmp[71] = ^tmp[70:0];
    end

    // register outputs on valid input
    always @(posedge clk or negedge rst_n) begin
        if (!rst_n) begin
            o_data_crypt <= 72'b0;
            i_valid_dataout <= 1'b0;
        end else begin
            if (i_valid_datain) begin
                o_data_crypt <= tmp;
                i_valid_dataout <= 1'b1;
            end else begin
                i_valid_dataout <= 1'b0;
            end
        end
    end

endmodule

SEC-DED/sec_ded_vivado/sec_ded_vivado.srcs/sim_1/new/tb_sec_enc.v

`timescale 1ns / 1ps

module tb_sec_enc;

    reg clk;
    reg rst_n;
    reg [63:0] i_data;
    reg i_valid_datain;

    wire i_valid_dataout;
    wire [71:0] o_data_crypt;

    // instantiate encoder
    sec_encoder uut (
        .clk(clk),
        .rst_n(rst_n),
        .i_data(i_data),
        .i_valid_datain(i_valid_datain),
        .i_valid_dataout(i_valid_dataout),
        .o_data_crypt(o_data_crypt)
    );

    // clock
    initial begin
        clk = 0;
        forever #5 clk = ~clk; // 100MHz (10ns period)
    end

    // test stimulus
    initial begin
        $dumpfile("tb_sec_enc.vcd");
        $dumpvars(0, tb_sec_enc);

        // reset
        rst_n = 0;
        i_data = 64'h0;
        i_valid_datain = 0;
        #20;
        rst_n = 1;

        // test vectors
        send_and_capture(64'h0123_4567_89AB_CDEF);
        send_and_capture(64'hFFFF_FFFF_FFFF_FFFF);
        send_and_capture(64'h0000_0000_0000_0000);

        #50;
        $display("tb_sec_enc finished");
        $finish;
    end

    task send_and_capture(input [63:0] data);
        reg [71:0] cw;
        begin
            // drive data, then assert valid around the next positive edge (assert at negedge before the posedge)
            @(posedge clk);
            i_data = data;
            @(negedge clk);
            i_valid_datain = 1;
            @(posedge clk); // encoder will sample at this posedge and register outputs
            #1;
            i_valid_datain = 0;
            #1;
            cw = o_data_crypt;
            $display("ENCODE: data=0x%016h -> codeword=0x%018h (valid=%b)", data, cw, i_valid_dataout);
        end
    endtask

endmodule

SEC-DED/tb_sec_enc.vcd
$date
	Thu Nov 06 11:52:42 2025
$end
$version
	Icarus Verilog
$end
$timescale
	1ps
$end
$scope module tb_sec_enc $end
$var wire 72 ! o_data_crypt [71:0] $end
$var wire 1 " i_valid_dataout $end
$var reg 1 # clk $end
$var reg 64 $ i_data [63:0] $end
$var reg 1 % i_valid_datain $end
$var reg 1 & rst_n $end
$scope module uut $end
$var wire 1 # clk $end
$var wire 64 ' i_data [63:0] $end
$var wire 1 % i_valid_datain $end
$var wire 1 & rst_n $end
$var reg 1 " i_valid_dataout $end
$var reg 72 ( o_data_crypt [71:0] $end
$var reg 1 ) parity_bit $end
$var reg 72 * tmp [71:0] $end
$var integer 32 + d_idx [31:0] $end
$var integer 32 , p [31:0] $end
$var integer 32 - pos [31:0] $end
$scope begin Hamming_parity_compute $end
$var integer 32 . pow2 [31:0] $end
$upscope $end
$upscope $end
$scope task send_and_capture $end
$var reg 72 / cw [71:0] $end
$var reg 64 0 data [63:0] $end
$upscope $end
$upscope $end
$enddefinitions $end
#0
$dumpvars
bx 0
bx /
b1000000 .
b1001001 -
b111 ,
b1000000 +
b0 *
0)
b0 (
b0 '
0&
0%
b0 $
0#
0"
b0 !
$end
#5000
1#
#10000
0#
#15000
1#
#20000
0#
b100100011010001010110011110001001101010111100110111101111 0
1&
#25000
0)
b1000000 .
b111 ,
b100000000100100011010001010110011110001000110101011110011101111011111100 *
b1001001 -
b1000000 +
b100100011010001010110011110001001101010111100110111101111 $
b100100011010001010110011110001001101010111100110111101111 '
1#
#30000
1%
0#
#35000
1"
b100000000100100011010001010110011110001000110101011110011101111011111100 !
b100000000100100011010001010110011110001000110101011110011101111011111100 (
1#
#36000
0%
#37000
b1111111111111111111111111111111111111111111111111111111111111111 0
b100000000100100011010001010110011110001000110101011110011101111011111100 /
#40000
0#
#45000
0"
1)
b1000000 .
b111 ,
b1001001 -
b1000000 +
b111111111111111111111111111111111111111111111111111111111111111111111111 *
b1111111111111111111111111111111111111111111111111111111111111111 $
b1111111111111111111111111111111111111111111111111111111111111111 '
1#
#50000
1%
0#
#55000
1"
b111111111111111111111111111111111111111111111111111111111111111111111111 !
b111111111111111111111111111111111111111111111111111111111111111111111111 (
1#
#56000
0%
#57000
b0 0
b111111111111111111111111111111111111111111111111111111111111111111111111 /
#60000
0#
#65000
0"
0)
b1000000 .
b111 ,
b1001001 -
b1000000 +
b0 *
b0 $
b0 '
1#
#70000
1%
0#
#75000
1"
b0 !
b0 (
1#
#76000
0%
#77000
b0 /
#80000
0#
#85000
0"
1#
