SEC-DED/sec_ded_vivado/sec_ded_vivado.srcs/sources_1/new/sec_decoder_comb.v
`timescale 1ns / 1ps
//////////////////////////////////////////////////////////////////////////////////
// Company: 
// Engineer: 
// 
// Create Date: 2025/11/06 11:22:23
// Design Name: 
// Module Name: sec_decoder_comb
// Project Name: 
// Target Devices: 
// Tool Versions: 
// Description: 
// 
// Dependencies: 
// 
// Revision:
// Revision 0.01 - File Created
// Additional Comments:
// 
//////////////////////////////////////////////////////////////////////////////////


`timescale 1ns / 1ps

// Combinational SEC-DED decoder for codeword 72 -> data 64
// - Inputs: full 72-bit codeword (positions 1..72 -> bits [0..71])
// - Outputs: corrected 64-bit data, o_valid = 1 when correctable/no-error, o_uncorrectable = 1 when detected double-bit error
module sec_decoder_comb(
    input  [71:0] i_codeword,
    output reg [63:0] o_data,
    output reg o_valid,
    output reg o_uncorrectable
);
    integer pos, p, d_idx;
    reg [71:0] rec;
    reg [6:0] syndrome_bits;
    reg [6:0] syndrome_value;
    reg overall_parity;
    reg [71:0] corrected;
    reg [63:0] extracted;

    always @(*) begin
        rec = i_codeword;
        syndrome_bits = 7'b0;

        // compute syndrome bits: compare expected parity from data positions with received parity bits
        for (p = 0; p < 7; p = p + 1) begin
            integer pow2;
            reg parity_expected;
            reg parity_mismatch;
            pow2 = 1 << p;
            parity_expected = 1'b0;
            for (pos = 1; pos <= 71; pos = pos + 1) begin
                if (pos == 72 || (pos & (pos - 1)) == 0) begin
                    // skip parity and overall parity
                end else begin
                    if ((pos & pow2) != 0) parity_expected = parity_expected ^ rec[pos-1];
                end
            end
            parity_mismatch = parity_expected ^ rec[pow2-1];
            syndrome_bits[p] = parity_mismatch;
        end

        // syndrome value
        syndrome_value = 7'b0;
        for (p = 0; p < 7; p = p + 1) if (syndrome_bits[p]) syndrome_value = syndrome_value + (1<<p);

        // overall parity across all 72 bits
        overall_parity = ^rec;

        corrected = rec;
        o_uncorrectable = 1'b0;

        if (syndrome_value == 0) begin
            if (overall_parity == 1'b1) begin
                // overall parity bit wrong
                corrected[71] = ~rec[71];
            end
            // else no error
        end else begin
            if (overall_parity == 1'b1) begin
                // single-bit error at syndrome_value
                if (syndrome_value >= 1 && syndrome_value <= 72) corrected[syndrome_value-1] = ~rec[syndrome_value-1];
            end else begin
                // double-bit detected
                o_uncorrectable = 1'b1;
            end
        end

        // extract 64-bit data from corrected codeword
        d_idx = 0;
        extracted = 64'b0;
        for (pos = 1; pos <= 72; pos = pos + 1) begin
            if (pos == 72 || (pos & (pos - 1)) == 0) begin
                // skip parity / overall parity
            end else begin
                if (d_idx < 64) begin
                    extracted[d_idx] = corrected[pos-1];
                end
                d_idx = d_idx + 1;
            end
        end

        // valid if not uncorrectable
        if (o_uncorrectable) begin
            o_valid = 1'b0;
        end else begin
            o_valid = 1'b1;
        end

        o_data = extracted;
    end

endmodule

SEC-DED/sec_ded_vivado/sec_ded_vivado.srcs/sources_1/new/sec_encoder_comb.v
`timescale 1ns / 1ps
//////////////////////////////////////////////////////////////////////////////////
// Company: 
// Engineer: 
// 
// Create Date: 2025/11/06 11:22:23
// Design Name: 
// Module Name: sec_encoder_comb
// Project Name: 
// Target Devices: 
// Tool Versions: 
// Description: 
// 
// Dependencies: 
// 
// Revision:
// Revision 0.01 - File Created
// Additional Comments:
// 
//////////////////////////////////////////////////////////////////////////////////


`timescale 1ns / 1ps

// Combinational SEC-DED encoder (64 -> 72)
// - Codeword positions 1..72 map to vector bits [0]=pos1 .. [71]=pos72
// - Parity bits at positions 1,2,4,8,16,32,64 (powers of two)
// - Overall parity (even) at position 72
module sec_encoder_comb(
    input  [63:0] i_data,
    output reg [71:0] o_codeword
);
    integer pos, p, d_idx;
    reg [71:0] tmp;
    reg parity_bit;

    always @(*) begin
        tmp = 72'b0;
        // place data bits into non-parity positions
        d_idx = 0;
        for (pos = 1; pos <= 72; pos = pos + 1) begin
            if (pos == 72 || (pos & (pos - 1)) == 0) begin
                // parity / overall parity: leave for later
            end else begin
                if (d_idx < 64) tmp[pos-1] = i_data[d_idx];
                else tmp[pos-1] = 1'b0;
                d_idx = d_idx + 1;
            end
        end

        // compute Hamming parity bits using only data positions
        for (p = 0; p < 7; p = p + 1) begin
            integer pow2;
            pow2 = 1 << p;
            parity_bit = 1'b0;
            for (pos = 1; pos <= 71; pos = pos + 1) begin
                if (pos == 72 || (pos & (pos - 1)) == 0) begin
                    // skip parity positions and overall parity
                end else begin
                    if ((pos & pow2) != 0) parity_bit = parity_bit ^ tmp[pos-1];
                end
            end
            tmp[pow2-1] = parity_bit;
        end

        // overall parity (even) over positions 1..71
        tmp[71] = ^tmp[70:0];

        o_codeword = tmp;
    end

endmodule

SEC-DED/sec_ded_vivado/sec_ded_vivado.srcs/sim_1/new/tb_sec_dec_comb.v
`timescale 1ns / 1ps
//////////////////////////////////////////////////////////////////////////////////
// Company: 
// Engineer: 
// 
// Create Date: 2025/11/06 14:41:32
// Design Name: 
// Module Name: tb_sec_dec_comb
// Project Name: 
// Target Devices: 
// Tool Versions: 
// Description: 
// 
// Dependencies: 
// 
// Revision:
// Revision 0.01 - File Created
// Additional Comments:
// 
//////////////////////////////////////////////////////////////////////////////////


`timescale 1ns / 1ps

module tb_sec_dec_comb;
    reg [63:0] data_in;
    wire [71:0] cw;

    // combinational encoder and decoder
    sec_encoder_comb enc (.i_data(data_in), .o_codeword(cw));
    reg [71:0] cw_in;
    wire [63:0] dec_data;
    wire dec_valid;
    wire dec_uncorr;
    sec_decoder_comb dec (.i_codeword(cw_in), .o_data(dec_data), .o_valid(dec_valid), .o_uncorrectable(dec_uncorr));

    integer pass_count, fail_count;

    initial begin
        $dumpfile("tb_sec_dec_comb.vcd");
        $dumpvars(0, tb_sec_dec_comb);

        pass_count = 0; fail_count = 0;

        // test vectors
        run_case(64'h0123_4567_89AB_CDEF);
        run_case(64'h8000_0000_0000_0001);
        run_case(64'hFFFF_FFFF_FFFF_FFFF);
        run_case(64'h0000_0000_0000_0000);

        $display("COMBINATIONAL TB RESULT: pass=%0d fail=%0d", pass_count, fail_count);
        $finish;
    end

    task run_case(input [63:0] d);
        reg [71:0] cw_nom;
        reg [71:0] cw1;
        reg [71:0] cw2;
        integer b1, b2;
        begin
            data_in = d;
            #1; // wait for enc combinational output
            cw_nom = cw;
            $display("CASE: data=0x%016h codeword=0x%018h", d, cw_nom);

            // 1) no error
            cw_in = cw_nom;
            #1;
            if (dec_valid && dec_data == d && !dec_uncorr) begin
                $display("  [NO ERR] PASS"); pass_count = pass_count + 1;
            end else begin
                $display("  [NO ERR] FAIL: dec_data=0x%016h valid=%b uncorr=%b", dec_data, dec_valid, dec_uncorr); fail_count = fail_count + 1;
            end

            // 2) single-bit error
            cw1 = cw_nom;
            b1 = 10; // flip a data bit (index in codeword)
            cw1[b1] = ~cw1[b1];
            cw_in = cw1; #1;
            if (dec_valid && dec_data == d && !dec_uncorr) begin
                $display("  [1-BIT] PASS: corrected bit %0d", b1); pass_count = pass_count + 1;
            end else begin
                $display("  [1-BIT] FAIL: dec_data=0x%016h valid=%b uncorr=%b", dec_data, dec_valid, dec_uncorr); fail_count = fail_count + 1;
            end

            // 3) double-bit error
            cw2 = cw_nom;
            b1 = 12; b2 = 25;
            cw2[b1] = ~cw2[b1];
            cw2[b2] = ~cw2[b2];
            cw_in = cw2; #1;
            if (!dec_valid && dec_uncorr) begin
                $display("  [2-BIT] PASS: detected uncorrectable bits %0d,%0d", b1, b2); pass_count = pass_count + 1;
            end else begin
                $display("  [2-BIT] FAIL: dec_data=0x%016h valid=%b uncorr=%b", dec_data, dec_valid, dec_uncorr); fail_count = fail_count + 1;
            end

            #1;
        end
    endtask

endmodule

SEC-DED/tb_sec_dec_comb.vcd
$date
	Thu Nov 06 14:45:31 2025
$end
$version
	Icarus Verilog
$end
$timescale
	1ps
$end
$scope module tb_sec_dec_comb $end
$var wire 1 ! dec_valid $end
$var wire 1 " dec_uncorr $end
$var wire 64 # dec_data [63:0] $end
$var wire 72 $ cw [71:0] $end
$var reg 72 % cw_in [71:0] $end
$var reg 64 & data_in [63:0] $end
$var integer 32 ' fail_count [31:0] $end
$var integer 32 ( pass_count [31:0] $end
$scope module dec $end
$var wire 72 ) i_codeword [71:0] $end
$var reg 72 * corrected [71:0] $end
$var reg 64 + extracted [63:0] $end
$var reg 64 , o_data [63:0] $end
$var reg 1 " o_uncorrectable $end
$var reg 1 ! o_valid $end
$var reg 1 - overall_parity $end
$var reg 72 . rec [71:0] $end
$var reg 7 / syndrome_bits [6:0] $end
$var reg 7 0 syndrome_value [6:0] $end
$var integer 32 1 d_idx [31:0] $end
$var integer 32 2 p [31:0] $end
$var integer 32 3 pos [31:0] $end
$scope begin $unm_blk_8 $end
$var reg 1 4 parity_expected $end
$var reg 1 5 parity_mismatch $end
$var integer 32 6 pow2 [31:0] $end
$upscope $end
$upscope $end
$scope module enc $end
$var wire 64 7 i_data [63:0] $end
$var reg 72 8 o_codeword [71:0] $end
$var reg 1 9 parity_bit $end
$var reg 72 : tmp [71:0] $end
$var integer 32 ; d_idx [31:0] $end
$var integer 32 < p [31:0] $end
$var integer 32 = pos [31:0] $end
$scope begin $unm_blk_4 $end
$var integer 32 > pow2 [31:0] $end
$upscope $end
$upscope $end
$scope task run_case $end
$var reg 72 ? cw1 [71:0] $end
$var reg 72 @ cw2 [71:0] $end
$var reg 72 A cw_nom [71:0] $end
$var reg 64 B d [63:0] $end
$var integer 32 C b1 [31:0] $end
$var integer 32 D b2 [31:0] $end
$upscope $end
$upscope $end
$enddefinitions $end
#0
$dumpvars
bx D
bx C
b100100011010001010110011110001001101010111100110111101111 B
bx A
bx @
bx ?
b1000000 >
b1001000 =
b111 <
b1000000 ;
b100000000100100011010001010110011110001000110101011110011101111011111100 :
09
b100000000100100011010001010110011110001000110101011110011101111011111100 8
b100100011010001010110011110001001101010111100110111101111 7
bx 6
x5
x4
bx 3
bx 2
bx 1
bx 0
bx /
bx .
x-
bx ,
bx +
bx *
bx )
b0 (
b0 '
b100100011010001010110011110001001101010111100110111101111 &
bx %
b100000000100100011010001010110011110001000110101011110011101111011111100 $
bx #
x"
x!
$end
#1000
b100100011010001010110011110001001101010111100110111101111 #
b100100011010001010110011110001001101010111100110111101111 ,
1!
b100100011010001010110011110001001101010111100110111101111 +
b1000000 1
0"
b100000000100100011010001010110011110001000110101011110011101111011111100 *
0-
b0 0
05
b1001001 3
04
b1000000 6
b111 2
b0 /
b100000000100100011010001010110011110001000110101011110011101111011111100 .
b100000000100100011010001010110011110001000110101011110011101111011111100 %
b100000000100100011010001010110011110001000110101011110011101111011111100 )
b100000000100100011010001010110011110001000110101011110011101111011111100 A
#2000
b100100011010001010110011110001001101010111100110111101111 +
b1000000 1
b100000000100100011010001010110011110001000110101011110011101111011111100 *
1-
b1011 0
b1011 /
05
04
b1001001 3
b1000000 6
b111 2
b100000000100100011010001010110011110001000110101011110011101101011111100 .
b100000000100100011010001010110011110001000110101011110011101101011111100 %
b100000000100100011010001010110011110001000110101011110011101101011111100 )
b1010 C
b100000000100100011010001010110011110001000110101011110011101101011111100 ?
b1 (
#3000
b100100011010001010110011110001001101110111100110011101111 #
b100100011010001010110011110001001101110111100110011101111 ,
0!
b100100011010001010110011110001001101110111100110011101111 +
b1000000 1
1"
b100000000100100011010001010110011110001000110111011110011100111011111100 *
0-
b10111 0
05
04
b1001001 3
b1000000 6
b111 2
b10111 /
b100000000100100011010001010110011110001000110111011110011100111011111100 .
b100000000100100011010001010110011110001000110111011110011100111011111100 %
b100000000100100011010001010110011110001000110111011110011100111011111100 )
b11001 D
b1100 C
b100000000100100011010001010110011110001000110111011110011100111011111100 @
b10 (
#4000
b11 (
#5000
b10000001000000000000000000000000000000000000000000000000000000000001100 $
b10000001000000000000000000000000000000000000000000000000000000000001100 8
19
b1000000 >
b111 <
b1001000 =
b1000000 ;
b10000001000000000000000000000000000000000000000000000000000000000001100 :
b1000000000000000000000000000000000000000000000000000000000000001 &
b1000000000000000000000000000000000000000000000000000000000000001 7
b1000000000000000000000000000000000000000000000000000000000000001 B
#6000
b1000000000000000000000000000000000000000000000000000000000000001 #
b1000000000000000000000000000000000000000000000000000000000000001 ,
1!
b1000000000000000000000000000000000000000000000000000000000000001 +
b1000000 1
0"
b10000001000000000000000000000000000000000000000000000000000000000001100 *
b0 0
14
b1001001 3
b1000000 6
b111 2
b0 /
b10000001000000000000000000000000000000000000000000000000000000000001100 .
b10000001000000000000000000000000000000000000000000000000000000000001100 %
b10000001000000000000000000000000000000000000000000000000000000000001100 )
b10000001000000000000000000000000000000000000000000000000000000000001100 A
#7000
b1000000000000000000000000000000000000000000000000000000000000001 +
b1000000 1
b10000001000000000000000000000000000000000000000000000000000000000001100 *
1-
b1011 0
b1011 /
05
b1001001 3
14
b1000000 6
b111 2
b10000001000000000000000000000000000000000000000000000000000010000001100 .
b10000001000000000000000000000000000000000000000000000000000010000001100 %
b10000001000000000000000000000000000000000000000000000000000010000001100 )
b1010 C
b10000001000000000000000000000000000000000000000000000000000010000001100 ?
b100 (
#8000
b1000000000000000000000000000000000000000000100000000000100000001 #
b1000000000000000000000000000000000000000000100000000000100000001 ,
0!
b1000000000000000000000000000000000000000000100000000000100000001 +
b1000000 1
1"
b10000001000000000000000000000000000000000000010000000000001000000001100 *
0-
b10111 0
05
b1001001 3
14
b1000000 6
b111 2
b10111 /
b10000001000000000000000000000000000000000000010000000000001000000001100 .
b10000001000000000000000000000000000000000000010000000000001000000001100 %
b10000001000000000000000000000000000000000000010000000000001000000001100 )
b1100 C
b10000001000000000000000000000000000000000000010000000000001000000001100 @
b101 (
#9000
b110 (
#10000
b111111111111111111111111111111111111111111111111111111111111111111111111 $
b111111111111111111111111111111111111111111111111111111111111111111111111 8
19
b1000000 >
b111 <
b1001000 =
b1000000 ;
b111111111111111111111111111111111111111111111111111111111111111111111111 :
b1111111111111111111111111111111111111111111111111111111111111111 &
b1111111111111111111111111111111111111111111111111111111111111111 7
b1111111111111111111111111111111111111111111111111111111111111111 B
#11000
b1111111111111111111111111111111111111111111111111111111111111111 #
b1111111111111111111111111111111111111111111111111111111111111111 ,
1!
b1111111111111111111111111111111111111111111111111111111111111111 +
b1000000 1
0"
b111111111111111111111111111111111111111111111111111111111111111111111111 *
b0 0
b1001001 3
14
b1000000 6
b111 2
b0 /
b111111111111111111111111111111111111111111111111111111111111111111111111 .
b111111111111111111111111111111111111111111111111111111111111111111111111 %
b111111111111111111111111111111111111111111111111111111111111111111111111 )
b111111111111111111111111111111111111111111111111111111111111111111111111 A
#12000
b1111111111111111111111111111111111111111111111111111111111111111 +
b1000000 1
b111111111111111111111111111111111111111111111111111111111111111111111111 *
1-
b1011 0
b1011 /
05
b1001001 3
14
b1000000 6
b111 2
b111111111111111111111111111111111111111111111111111111111111101111111111 .
b111111111111111111111111111111111111111111111111111111111111101111111111 %
b111111111111111111111111111111111111111111111111111111111111101111111111 )
b1010 C
b111111111111111111111111111111111111111111111111111111111111101111111111 ?
b111 (
#13000
b1111111111111111111111111111111111111111111011111111111011111111 #
b1111111111111111111111111111111111111111111011111111111011111111 ,
0!
b1111111111111111111111111111111111111111111011111111111011111111 +
b1000000 1
1"
b111111111111111111111111111111111111111111111101111111111110111111111111 *
0-
b10111 0
05
b1001001 3
14
b1000000 6
b111 2
b10111 /
b111111111111111111111111111111111111111111111101111111111110111111111111 .
b111111111111111111111111111111111111111111111101111111111110111111111111 %
b111111111111111111111111111111111111111111111101111111111110111111111111 )
b1100 C
b111111111111111111111111111111111111111111111101111111111110111111111111 @
b1000 (
#14000
b1001 (
#15000
b0 $
b0 8
09
b1000000 >
b111 <
b1001000 =
b1000000 ;
b0 :
b0 &
b0 7
b0 B
#16000
b0 #
b0 ,
1!
b0 +
b1000000 1
0"
b0 *
b0 0
b1001001 3
04
b1000000 6
b111 2
b0 /
b0 .
b0 %
b0 )
b0 A
#17000
b1000000 1
b0 *
1-
b1011 0
b1011 /
05
04
b1001001 3
b1000000 6
b111 2
b10000000000 .
b10000000000 %
b10000000000 )
b1010 C
b10000000000 ?
b1010 (
#18000
b100000000000100000000 #
b100000000000100000000 ,
0!
b100000000000100000000 +
b1000000 1
1"
b10000000000001000000000000 *
0-
b10111 0
05
04
b1001001 3
b1000000 6
b111 2
b10111 /
b10000000000001000000000000 .
b10000000000001000000000000 %
b10000000000001000000000000 )
b1100 C
b10000000000001000000000000 @
b1011 (
#19000
b1100 (
