SEC-DED/sec_ded_vivado/sec_ded_vivado.srcs/sources_1/new/ser_parral_trans.v
`timescale 1ns / 1ps
//////////////////////////////////////////////////////////////////////////////////
// Company: 
// Engineer: 
// 
// Create Date: 2025/11/06 11:13:51
// Design Name: 
// Module Name: ser_parral_trans
// Project Name: 
// Target Devices: 
// Tool Versions: 
// Description: 
// 
// Dependencies: 
// 
// Revision:
// Revision 0.01 - File Created
// Additional Comments:
// 
//////////////////////////////////////////////////////////////////////////////////


module ser_parral_trans
(
    input clk
,   input rst_n

,   output reg [63:0] o_data_decrypt
,   output reg o_valid_datain

,   input i_valid_dataout
,   input [71:0] i_data_crypt
    );
    // The decoder implements SEC-DED for the codeword layout produced by sec_encoder.v
    // - Codeword positions 1..72 (vector index 0..71)
    // - Parity bits at positions 1,2,4,8,16,32,64
    // - Overall parity at position 72
    // Behavior:
    // - On i_valid_dataout asserted, compute syndrome and overall parity.
    // - If single-bit error, correct it and extract 64-bit data.
    // - If double-bit error detected (uncorrectable), output data as-is and deassert valid (or still raise valid but user may check error flag if added).

    integer pos, p, d_idx;
    reg [71:0] rec;
    reg [6:0] syndrome_bits;
    reg [6:0] syndrome_value_bin;
    reg overall_parity;
    reg [71:0] corrected;
    reg uncorrectable;

    always @(*) begin
        rec = i_data_crypt;
        syndrome_bits = 7'b0;
        // compute syndrome bits based on data positions only (skip parity positions and overall parity)
        for (p = 0; p < 7; p = p + 1) begin
            integer pow2;
            reg parity_expected;
            reg parity_mismatch;
            pow2 = 1 << p;
            parity_expected = 1'b0;
            for (pos = 1; pos <= 71; pos = pos + 1) begin
                // skip parity positions and overall parity (71 is last data position index)
                if (pos == 72 || (pos & (pos - 1)) == 0) begin
                    // skip
                end else begin
                    if ((pos & pow2) != 0) begin
                        parity_expected = parity_expected ^ rec[pos-1];
                    end
                end
            end
            // compare expected parity (from data) with received parity bit at pow2
            parity_mismatch = parity_expected ^ rec[pow2-1];
            syndrome_bits[p] = parity_mismatch; // 1 if mismatch
        end

        // convert syndrome bits into numeric position (1-based)
        syndrome_value_bin = 7'b0;
        for (p = 0; p < 7; p = p + 1) begin
            if (syndrome_bits[p]) begin
                syndrome_value_bin = syndrome_value_bin + (1 << p);
            end
        end

        // overall parity computed across full received word; for even parity should be 0 when correct
        overall_parity = ^rec; // XOR of all 72 bits

        corrected = rec;
        uncorrectable = 1'b0;

        if (syndrome_value_bin == 0) begin
            if (overall_parity == 1'b1) begin
                // error only in overall parity bit (position 72) -> flip it
                corrected[71] = ~rec[71];
            end else begin
                // no error
            end
        end else begin
            if (overall_parity == 1'b1) begin
                // single-bit error at syndrome_value_bin -> correct
                if (syndrome_value_bin >= 1 && syndrome_value_bin <= 72) begin
                    corrected[syndrome_value_bin - 1] = ~rec[syndrome_value_bin - 1];
                end
            end else begin
                // syndrome != 0 but overall parity == 0 -> detected double-bit error (uncorrectable)
                uncorrectable = 1'b1;
            end
        end
    end

    // extract data bits from corrected word in same mapping as encoder
    reg [63:0] extracted;
    always @(*) begin
        d_idx = 0;
        extracted = 64'b0;
        for (pos = 1; pos <= 72; pos = pos + 1) begin
            if (pos == 72 || (pos & (pos - 1)) == 0) begin
                // parity / overall parity -> skip
            end else begin
                if (d_idx < 64) begin
                    extracted[d_idx] = corrected[pos-1];
                end
                d_idx = d_idx + 1;
            end
        end
    end

    // register outputs synchronously
    always @(posedge clk or negedge rst_n) begin
        if (!rst_n) begin
            o_data_decrypt <= 64'b0;
            o_valid_datain <= 1'b0;
        end else begin
            if (i_valid_dataout) begin
                if (uncorrectable) begin
                    // for an uncorrectable error we still present the extracted data but clear the valid flag
                    // Alternatively, user can add an explicit error output to signal uncorrectable condition.
                    o_data_decrypt <= extracted;
                    o_valid_datain <= 1'b0;
                end else begin
                    o_data_decrypt <= extracted;
                    o_valid_datain <= 1'b1;
                end
            end else begin
                o_valid_datain <= 1'b0;
            end
        end
    end

endmodule

SEC-DED/sec_ded_vivado/sec_ded_vivado.srcs/sources_1/new/sec_encoder.v
`timescale 1ns / 1ps
//////////////////////////////////////////////////////////////////////////////////
// Company: 
// Engineer: 
// 
// Create Date: 2025/11/06 11:13:51
// Design Name: 
// Module Name: sec_encoder
// Project Name: 
// Target Devices: 
// Tool Versions: 
// Description: 
// 
// Dependencies: 
// 
// Revision:
// Revision 0.01 - File Created
// Additional Comments:
// 
//////////////////////////////////////////////////////////////////////////////////


module sec_encoder
(
    input clk
,   input rst_n

,   input [63:0] i_data
,   input i_valid_datain

,   output reg i_valid_dataout
,   output reg [71:0] o_data_crypt
    );
// Implementation notes:
// - Codeword positions are 1..72 (1-based). We map them into vector indexes [0]=pos1 ... [71]=pos72.
// - Parity bits (Hamming) are placed at positions 1,2,4,8,16,32,64 (powers of two).
// - Overall parity (for DED) is placed at position 72 (the last bit).
// - Data bits (64 bits) are filled into positions that are NOT the parity positions nor position 72,
//   in ascending order: i_data[0] -> lowest data position, etc. The decoder uses the same mapping.

    integer pos, p, d_idx;
    reg [71:0] tmp;
    reg parity_bit;

    always @(*) begin
        // clear
        tmp = 72'b0;
        // place data bits into non-parity positions (positions 1..72, skip powers of two and pos 72)
        d_idx = 0;
        for (pos = 1; pos <= 72; pos = pos + 1) begin
            // skip parity positions 1,2,4,8,16,32,64 and overall parity pos 72
            if (pos == 72 || (pos & (pos - 1)) == 0) begin
                // parity / overall parity: leave for later
            end else begin
                if (d_idx < 64) begin
                    tmp[pos-1] = i_data[d_idx];
                end else begin
                    tmp[pos-1] = 1'b0; // safety
                end
                d_idx = d_idx + 1;
            end
        end

        // compute Hamming parity bits for positions 1,2,4,8,16,32,64
        // Only XOR data bit positions (skip all parity positions and overall parity at pos 72)
        for (p = 0; p < 7; p = p + 1) begin:Hamming_parity_compute
            integer pow2;
            pow2 = 1 << p; // parity position (1-based)
            parity_bit = 1'b0;
            for (pos = 1; pos <= 72; pos = pos + 1) begin
                // skip parity positions and overall parity
                if (pos == pow2 || pos == 72 || (pos & (pos - 1)) == 0) begin
                    // skip parity/overall parity positions
                end else begin
                    if ((pos & pow2) != 0) begin
                        parity_bit = parity_bit ^ tmp[pos-1];
                    end
                end
            end
            tmp[pow2-1] = parity_bit; // write parity
        end

        // compute overall parity (even) placed at position 72
        // overall parity is XOR of bits at positions 1..71 (first 71 bits)
        tmp[71] = ^tmp[70:0];
    end

    // register outputs on valid input
    always @(posedge clk or negedge rst_n) begin
        if (!rst_n) begin
            o_data_crypt <= 72'b0;
            i_valid_dataout <= 1'b0;
        end else begin
            if (i_valid_datain) begin
                o_data_crypt <= tmp;
                i_valid_dataout <= 1'b1;
            end else begin
                i_valid_dataout <= 1'b0;
            end
        end
    end

endmodule

SEC-DED/sec_ded_vivado/sec_ded_vivado.srcs/sim_1/new/tb_sec_dec.v
`timescale 1ns / 1ps
//////////////////////////////////////////////////////////////////////////////////
// Company: 
// Engineer: 
// 
// Create Date: 2025/11/06 11:26:26
// Design Name: 
// Module Name: tb_sec_dec
// Project Name: 
// Target Devices: 
// Tool Versions: 
// Description: 
// 
// Dependencies: 
// 
// Revision:
// Revision 0.01 - File Created
// Additional Comments:
// 
//////////////////////////////////////////////////////////////////////////////////


// Testbench for encoder + decoder with error injection
`timescale 1ns / 1ps

module tb_sec_dec;

    reg clk;
    reg rst_n;
    reg [63:0] i_data;
    reg i_valid_datain;

    wire enc_valid;
    wire [71:0] enc_cw;

    // decoder inputs
    reg dec_valid_in;
    reg [71:0] dec_cw_in;

    wire [63:0] dec_data_out;
    wire dec_valid_out;

    // instantiate encoder
    sec_encoder enc (
        .clk(clk),
        .rst_n(rst_n),
        .i_data(i_data),
        .i_valid_datain(i_valid_datain),
        .i_valid_dataout(enc_valid),
        .o_data_crypt(enc_cw)
    );

    // instantiate decoder
    ser_parral_trans dec (
        .clk(clk),
        .rst_n(rst_n),
        .o_data_decrypt(dec_data_out),
        .o_valid_datain(dec_valid_out),
        .i_valid_dataout(dec_valid_in),
        .i_data_crypt(dec_cw_in)
    );

    // clock
    initial begin
        clk = 0;
        forever #5 clk = ~clk;
    end

    initial begin
        $dumpfile("tb_sec_dec.vcd");
        $dumpvars(0, tb_sec_dec);

        // reset
        rst_n = 0;
        i_data = 64'h0;
        i_valid_datain = 0;
        dec_valid_in = 0;
        dec_cw_in = 72'h0;
        #20;
        rst_n = 1;

        // testcases
        test_case(64'h0123_4567_89AB_CDEF);
        test_case(64'h8000_0000_0000_0001);

        #100;
        $display("tb_sec_dec finished");
        $finish;
    end

    task test_case(input [63:0] data);
        reg [71:0] cw;
        reg [71:0] cw_single_err;
        reg [71:0] cw_double_err;
        integer b1, b2;
        begin
            // drive encoder (stable data before posedge, assert valid at negedge so posedge samples it)
            @(posedge clk);
            i_data = data;
            @(negedge clk);
            i_valid_datain = 1;
            @(posedge clk); // encoder samples and registers outputs
            #1;
            i_valid_datain = 0;
            #1;
            cw = enc_cw;
            $display("TEST: data=0x%016h -> codeword=0x%018h (enc_valid=%b)", data, cw, enc_valid);
            // compute and display syndrome/overall parity in TB for debugging
            compute_syndrome_and_parity(cw);
            check_encoder_parity(cw);

            // 1) no error
            // present codeword to decoder and assert valid around next posedge
            @(posedge clk);
            dec_cw_in = cw;
            @(negedge clk);
            dec_valid_in = 1;
            @(posedge clk);
            #1;
            dec_valid_in = 0;
            #1;
            if (dec_valid_out && dec_data_out == data) begin
                $display("  [NO ERR] PASS: decoded=0x%016h", dec_data_out);
            end else begin
                $display("  [NO ERR] FAIL: decoded=0x%016h valid=%b expected=0x%016h", dec_data_out, dec_valid_out, data);
            end

            // 2) single-bit error -> should be corrected
            cw_single_err = cw;
            b1 = 10; // flip bit 10
            cw_single_err[b1] = ~cw_single_err[b1];
            // single-bit error injection: present at negedge before posedge sampling
            @(posedge clk);
            dec_cw_in = cw_single_err;
            @(negedge clk);
            dec_valid_in = 1;
            @(posedge clk);
            #1;
            dec_valid_in = 0;
            #1;
            if (dec_valid_out && dec_data_out == data) begin
                $display("  [1-BIT] PASS: single-bit at %0d corrected -> decoded=0x%016h", b1, dec_data_out);
            end else begin
                $display("  [1-BIT] FAIL: decoded=0x%016h valid=%b expected=0x%016h", dec_data_out, dec_valid_out, data);
            end

            // 3) double-bit error -> should be detected as uncorrectable (decoder sets valid=0 in our implementation)
            cw_double_err = cw;
            b1 = 12; b2 = 25;
            cw_double_err[b1] = ~cw_double_err[b1];
            cw_double_err[b2] = ~cw_double_err[b2];
            // double-bit error injection
            @(posedge clk);
            dec_cw_in = cw_double_err;
            @(negedge clk);
            dec_valid_in = 1;
            @(posedge clk);
            #1;
            dec_valid_in = 0;
            #1;
            if (!dec_valid_out) begin
                $display("  [2-BIT] PASS: double-bit at %0d,%0d detected as uncorrectable (valid=0)", b1, b2);
            end else begin
                $display("  [2-BIT] FAIL: decoder reported valid=1 decoded=0x%016h (expected invalid)", dec_data_out);
            end

            #20;
        end
    endtask

    // helper: compute syndrome and overall parity for given codeword and display
    task compute_syndrome_and_parity(input [71:0] cw_in);
        integer p, pos;
        reg [6:0] synb;
        integer sval;
        reg overall;
        begin
            synb = 7'b0;
            for (p = 0; p < 7; p = p + 1) begin
                integer pow2;
                integer pos2;
                reg pc;
                pow2 = 1 << p;
                pc = 1'b0;
                for (pos2 = 1; pos2 <= 72; pos2 = pos2 + 1) begin
                    if ((pos2 & pow2) != 0) pc = pc ^ cw_in[pos2-1];
                end
                synb[p] = pc;
            end
            sval = 0;
            for (p = 0; p < 7; p = p + 1) if (synb[p]) sval = sval + (1<<p);
            overall = ^cw_in;
            $display("    TB SYNDROME: bits=%b value=%0d overall_parity=%b", synb, sval, overall);
        end
    endtask

    // Compute expected parity bits from data positions and compare to parity bits embedded in codeword
    task check_encoder_parity(input [71:0] cw_in);
        integer p, pos;
        integer pow2;
        reg expected;
        begin
            $display("    TB PARITY CHECK: parity positions (pos:value) and expected from data");
            for (p = 0; p < 7; p = p + 1) begin
                pow2 = 1 << p;
                expected = 1'b0;
                for (pos = 1; pos <= 72; pos = pos + 1) begin
                    // only data positions (skip parity positions and pos72)
                    if (pos == 72 || (pos & (pos - 1)) == 0) begin
                        // skip
                    end else begin
                        if ((pos & pow2) != 0) expected = expected ^ cw_in[pos-1];
                    end
                end
                $display("      pos%0d: enc=%b expected=%b", pow2, cw_in[pow2-1], expected);
            end
        end
    endtask

endmodule

SEC-DED/tb_sec_dec.vcd
$date
	Thu Nov 06 14:14:46 2025
$end
$version
	Icarus Verilog
$end
$timescale
	1ps
$end
$scope module tb_sec_dec $end
$var wire 1 ! enc_valid $end
$var wire 72 " enc_cw [71:0] $end
$var wire 1 # dec_valid_out $end
$var wire 64 $ dec_data_out [63:0] $end
$var reg 1 % clk $end
$var reg 72 & dec_cw_in [71:0] $end
$var reg 1 ' dec_valid_in $end
$var reg 64 ( i_data [63:0] $end
$var reg 1 ) i_valid_datain $end
$var reg 1 * rst_n $end
$scope module dec $end
$var wire 1 % clk $end
$var wire 72 + i_data_crypt [71:0] $end
$var wire 1 ' i_valid_dataout $end
$var wire 1 * rst_n $end
$var reg 72 , corrected [71:0] $end
$var reg 64 - extracted [63:0] $end
$var reg 64 . o_data_decrypt [63:0] $end
$var reg 1 # o_valid_datain $end
$var reg 1 / overall_parity $end
$var reg 72 0 rec [71:0] $end
$var reg 7 1 syndrome_bits [6:0] $end
$var reg 7 2 syndrome_value_bin [6:0] $end
$var reg 1 3 uncorrectable $end
$var integer 32 4 d_idx [31:0] $end
$var integer 32 5 p [31:0] $end
$var integer 32 6 pos [31:0] $end
$scope begin $unm_blk_15 $end
$var reg 1 7 parity_expected $end
$var reg 1 8 parity_mismatch $end
$var integer 32 9 pow2 [31:0] $end
$upscope $end
$upscope $end
$scope module enc $end
$var wire 1 % clk $end
$var wire 64 : i_data [63:0] $end
$var wire 1 ) i_valid_datain $end
$var wire 1 * rst_n $end
$var reg 1 ! i_valid_dataout $end
$var reg 72 ; o_data_crypt [71:0] $end
$var reg 1 < parity_bit $end
$var reg 72 = tmp [71:0] $end
$var integer 32 > d_idx [31:0] $end
$var integer 32 ? p [31:0] $end
$var integer 32 @ pos [31:0] $end
$scope begin Hamming_parity_compute $end
$var integer 32 A pow2 [31:0] $end
$upscope $end
$upscope $end
$scope task check_encoder_parity $end
$var reg 72 B cw_in [71:0] $end
$var reg 1 C expected $end
$var integer 32 D p [31:0] $end
$var integer 32 E pos [31:0] $end
$var integer 32 F pow2 [31:0] $end
$upscope $end
$scope task compute_syndrome_and_parity $end
$var reg 72 G cw_in [71:0] $end
$var reg 1 H overall $end
$var reg 7 I synb [6:0] $end
$var integer 32 J p [31:0] $end
$var integer 32 K sval [31:0] $end
$scope begin $unm_blk_48 $end
$var reg 1 L pc $end
$var integer 32 M pos2 [31:0] $end
$var integer 32 N pow2 [31:0] $end
$upscope $end
$upscope $end
$scope task test_case $end
$var reg 72 O cw [71:0] $end
$var reg 72 P cw_double_err [71:0] $end
$var reg 72 Q cw_single_err [71:0] $end
$var reg 64 R data [63:0] $end
$var integer 32 S b1 [31:0] $end
$var integer 32 T b2 [31:0] $end
$upscope $end
$upscope $end
$enddefinitions $end
#0
$dumpvars
bx T
bx S
bx R
bx Q
bx P
bx O
bx N
bx M
xL
bx K
bx J
bx I
xH
bx G
bx F
bx E
bx D
xC
bx B
b1000000 A
b1001001 @
b111 ?
b1000000 >
b0 =
0<
b0 ;
b0 :
b1000000 9
08
07
b1001001 6
b111 5
b1000000 4
03
b0 2
b0 1
b0 0
0/
b0 .
b0 -
b0 ,
b0 +
0*
0)
b0 (
0'
b0 &
0%
b0 $
0#
b0 "
0!
$end
#5000
1%
#10000
0%
#15000
1%
#20000
0%
b100100011010001010110011110001001101010111100110111101111 R
1*
#25000
0<
b1000000 A
b111 ?
b100000000100100011010001010110011110001000110101011110011101111011111100 =
b1001001 @
b1000000 >
b100100011010001010110011110001001101010111100110111101111 (
b100100011010001010110011110001001101010111100110111101111 :
1%
#30000
1)
0%
#35000
1!
b100000000100100011010001010110011110001000110101011110011101111011111100 "
b100000000100100011010001010110011110001000110101011110011101111011111100 ;
1%
#36000
0)
#37000
b1001001 E
0C
b1000000 F
b111 D
b100000000100100011010001010110011110001000110101011110011101111011111100 B
0H
b1001000 K
b1001001 M
1L
b1000000 N
b111 J
b1001000 I
b100000000100100011010001010110011110001000110101011110011101111011111100 G
b100000000100100011010001010110011110001000110101011110011101111011111100 O
#40000
0%
#45000
0!
b100100011010001010110011110001001101010111100110111101111 -
b1000000 4
b100000000100100011010001010110011110001000110101011110011101111011111100 ,
07
b1001001 6
b1000000 9
b111 5
b100000000100100011010001010110011110001000110101011110011101111011111100 0
b100000000100100011010001010110011110001000110101011110011101111011111100 &
b100000000100100011010001010110011110001000110101011110011101111011111100 +
1%
#50000
1'
0%
#55000
1#
b100100011010001010110011110001001101010111100110111101111 $
b100100011010001010110011110001001101010111100110111101111 .
1%
#56000
0'
#57000
b1010 S
b100000000100100011010001010110011110001000110101011110011101101011111100 Q
#60000
0%
#65000
0#
b100100011010001010110011110001001101010111100110111101111 -
b1000000 4
b100000000100100011010001010110011110001000110101011110011101111011111100 ,
1/
b1011 2
b1011 1
08
07
b1001001 6
b1000000 9
b111 5
b100000000100100011010001010110011110001000110101011110011101101011111100 0
b100000000100100011010001010110011110001000110101011110011101101011111100 &
b100000000100100011010001010110011110001000110101011110011101101011111100 +
1%
#70000
1'
0%
#75000
1#
1%
#76000
0'
#77000
b11001 T
b1100 S
b100000000100100011010001010110011110001000110111011110011100111011111100 P
#80000
0%
#85000
0#
b100100011010001010110011110001001101110111100110011101111 -
b1000000 4
13
b100000000100100011010001010110011110001000110111011110011100111011111100 ,
0/
b10111 2
08
07
b1001001 6
b1000000 9
b111 5
b10111 1
b100000000100100011010001010110011110001000110111011110011100111011111100 0
b100000000100100011010001010110011110001000110111011110011100111011111100 &
b100000000100100011010001010110011110001000110111011110011100111011111100 +
1%
#90000
1'
0%
#95000
b100100011010001010110011110001001101110111100110011101111 $
b100100011010001010110011110001001101110111100110011101111 .
1%
#96000
0'
#100000
0%
#105000
1%
#110000
0%
#115000
1%
#117000
b1000000000000000000000000000000000000000000000000000000000000001 R
#120000
0%
#125000
1<
b1000000 A
b111 ?
b1001001 @
b1000000 >
b10000001000000000000000000000000000000000000000000000000000000000001100 =
b1000000000000000000000000000000000000000000000000000000000000001 (
b1000000000000000000000000000000000000000000000000000000000000001 :
1%
#130000
1)
0%
#135000
1!
b10000001000000000000000000000000000000000000000000000000000000000001100 "
b10000001000000000000000000000000000000000000000000000000000000000001100 ;
1%
#136000
0)
#137000
1C
b1001001 E
b1000000 F
b111 D
b10000001000000000000000000000000000000000000000000000000000000000001100 B
b0 K
b1001001 M
0L
b1000000 N
b111 J
b0 I
b10000001000000000000000000000000000000000000000000000000000000000001100 G
b10000001000000000000000000000000000000000000000000000000000000000001100 O
#140000
0%
#145000
0!
b1000000000000000000000000000000000000000000000000000000000000001 -
b1000000 4
03
b10000001000000000000000000000000000000000000000000000000000000000001100 ,
b0 2
17
b1001001 6
b1000000 9
b111 5
b0 1
b10000001000000000000000000000000000000000000000000000000000000000001100 0
b10000001000000000000000000000000000000000000000000000000000000000001100 &
b10000001000000000000000000000000000000000000000000000000000000000001100 +
1%
#150000
1'
0%
#155000
1#
b1000000000000000000000000000000000000000000000000000000000000001 $
b1000000000000000000000000000000000000000000000000000000000000001 .
1%
#156000
0'
#157000
b1010 S
b10000001000000000000000000000000000000000000000000000000000010000001100 Q
#160000
0%
#165000
0#
b1000000000000000000000000000000000000000000000000000000000000001 -
b1000000 4
b10000001000000000000000000000000000000000000000000000000000000000001100 ,
1/
b1011 2
b1011 1
08
b1001001 6
17
b1000000 9
b111 5
b10000001000000000000000000000000000000000000000000000000000010000001100 0
b10000001000000000000000000000000000000000000000000000000000010000001100 &
b10000001000000000000000000000000000000000000000000000000000010000001100 +
1%
#170000
1'
0%
#175000
1#
1%
#176000
0'
#177000
b1100 S
b10000001000000000000000000000000000000000000010000000000001000000001100 P
#180000
0%
#185000
0#
b1000000000000000000000000000000000000000000100000000000100000001 -
b1000000 4
13
b10000001000000000000000000000000000000000000010000000000001000000001100 ,
0/
b10111 2
08
b1001001 6
17
b1000000 9
b111 5
b10111 1
b10000001000000000000000000000000000000000000010000000000001000000001100 0
b10000001000000000000000000000000000000000000010000000000001000000001100 &
b10000001000000000000000000000000000000000000010000000000001000000001100 +
1%
#190000
1'
0%
#195000
b1000000000000000000000000000000000000000000100000000000100000001 $
b1000000000000000000000000000000000000000000100000000000100000001 .
1%
#196000
0'
